complexitest/__init__.py
complexitest/estimator.py
complexitest/timer.py
complexity_estimator/__init__.py
complexity_estimator/estimator.py
complexity_estimator/timer.py
complexitest-0.0.2.dist-info/METADATA
complexitest-0.0.2.dist-info/WHEEL
complexitest-0.0.2.dist-info/top_level.txt
complexitest-0.0.2.dist-info/RECORD
